{
    "PLY_1084": {
        "age": 23,
        "familiarity": {},
        "graphics": {
            "accessories": [],
            "beard_color": "#282828",
            "beard_type": "player_goatee_ing",
            "boot_color": "#5893EC",
            "boot_logo1_color": "#FFFFFF",
            "boot_logo1_type": "boots_logo2_ing",
            "boot_logo2_color": "#FFFFFF",
            "boot_logo2_type": "None",
            "boot_type": "player_boots_run_ing",
            "hair_color": "#282828",
            "hair_type": "hair_curlytop",
            "skin_color": "#DCAF88"
        },
        "height_cm": 172,
        "loyalty": 98,
        "name": "Vitinha",
        "nationality": "POR",
        "number": 10,
        "playstyle": "Quick Passer",
        "position": "Center Mid",
        "preferred_foot": "Right",
        "sharpness": 99,
        "stats": {
            "acceleration": 91.0,
            "aggression": 48.0,
            "agility": 88.0,
            "awareness": 88.0,
            "balancing": 93.0,
            "ball_control": 88.0,
            "blocking": 62.0,
            "body_strength": 71.0,
            "curl": 83.0,
            "dead_ball": 61.0,
            "finishing": 48.0,
            "fitness": 88.0,
            "gk_awareness": 0.0,
            "gk_blocking": 0.0,
            "gk_catching": 0.0,
            "gk_coverage": 0.0,
            "gk_reactions": 0.0,
            "gk_throwing": 0.0,
            "heading": 43.0,
            "injury_resistance": 3,
            "jumping_strength": 57.0,
            "kick_power": 72.0,
            "long_passing": 86.0,
            "short_passing": 91.0,
            "top_speed": 81.0,
            "weak_foot_accuracy": 4
        },
        "tactical_familiarity": 100.0,
        "team_id": "TEAM_111",
        "traits": [],
        "weight_kg": 67
    }
}