{
    "PLY_1014": {
        "age": 22,
        "familiarity": {
            "Center Back": 1,
            "Center Forward": 2,
            "Center Mid": 4,
            "Defensive Mid": 3,
            "Goalkeeper": 1,
            "Left Back": 1,
            "Left Mid": 3,
            "Left Wing": 2,
            "Left Wing Back": 1,
            "Right Back": 1,
            "Right Mid": 4,
            "Right Wing": 4,
            "Right Wing Back": 1,
            "Striker": 1
        },
        "graphics": {
            "accessories": [],
            "beard_color": "#282828",
            "beard_type": "Beard_None",
            "boot_color": "#000000",
            "boot_type": "Boots_Basic",
            "face_type": "Face_01",
            "hair_color": "#282828",
            "hair_type": "Hair_Short",
            "skin_color": "#FFE0BD"
        },
        "height_cm": 178,
        "loyalty": 95,
        "name": "M. Rapciak",
        "nationality": "POL",
        "number": 10,
        "playstyle": "Playmaker AM",
        "position": "Attacking Mid",
        "preferred_foot": "Right",
        "sharpness": 99,
        "stats": {
            "acceleration": 85.0,
            "aggression": 32.0,
            "agility": 68.0,
            "awareness": 51.0,
            "balancing": 59.0,
            "ball_control": 48.0,
            "blocking": 28.0,
            "body_strength": 45.0,
            "curl": 55.0,
            "dead_ball": 43.0,
            "finishing": 36.0,
            "fitness": 49.0,
            "gk_awareness": 0.0,
            "gk_blocking": 0.0,
            "gk_catching": 0.0,
            "gk_coverage": 0.0,
            "gk_reactions": 0.0,
            "gk_throwing": 0.0,
            "heading": 25.0,
            "injury_resistance": 4,
            "jumping_strength": 32.0,
            "kick_power": 48.0,
            "long_passing": 57.0,
            "short_passing": 59.0,
            "top_speed": 84.0,
            "weak_foot_accuracy": 4
        },
        "tactical_familiarity": 86.0,
        "team_id": "TEAM_102",
        "traits": [],
        "weight_kg": 65
    }
}