{
    "PLY_1035": {
        "age": 17,
        "graphics": {
            "accessories": [],
            "beard_color": "#282828",
            "beard_type": "Beard_None",
            "boot_color": "#000000",
            "boot_type": "Boots_Basic",
            "face_type": "Face_01",
            "hair_color": "#282828",
            "hair_type": "Hair_Short",
            "skin_color": "#674D2A"
        },
        "height_cm": 178,
        "loyalty": 95,
        "name": "R. Ngumoha",
        "number": 42,
        "playstyle": "Joga Bonito",
        "position": "Left Wing",
        "preferred_foot": "Right",
        "sharpness": 99,
        "stats": {
            "acceleration": 92.0,
            "aggression": 28.0,
            "agility": 88.0,
            "awareness": 73.0,
            "balancing": 83.0,
            "ball_control": 84.0,
            "blocking": 7.0,
            "body_strength": 46.0,
            "curl": 83.0,
            "dead_ball": 60.0,
            "finishing": 73.0,
            "fitness": 77.0,
            "gk_awareness": 0.0,
            "gk_blocking": 0.0,
            "gk_catching": 0.0,
            "gk_coverage": 0.0,
            "gk_reactions": 0.0,
            "gk_throwing": 0.0,
            "heading": 52.0,
            "injury_resistance": 3,
            "jumping_strength": 55.0,
            "kick_power": 76.0,
            "long_passing": 66.0,
            "short_passing": 72.0,
            "top_speed": 85.0,
            "weak_foot_accuracy": 3
        },
        "team_id": "TEAM_101",
        "traits": [],
        "weight_kg": 69
    }
}